odoo/addons/sale_purchase_requisition/README.rst
odoo/addons/sale_purchase_requisition/__init__.py
odoo/addons/sale_purchase_requisition/__manifest__.py
odoo/addons/sale_purchase_requisition/i18n/es.po
odoo/addons/sale_purchase_requisition/i18n/sale_purchase_requisition.pot
odoo/addons/sale_purchase_requisition/models/__init__.py
odoo/addons/sale_purchase_requisition/models/purchase_requisition.py
odoo/addons/sale_purchase_requisition/models/sale_order.py
odoo/addons/sale_purchase_requisition/readme/CONTRIBUTORS.rst
odoo/addons/sale_purchase_requisition/readme/CREDITS.rst
odoo/addons/sale_purchase_requisition/readme/DESCRIPTION.rst
odoo/addons/sale_purchase_requisition/readme/INSTALL.rst
odoo/addons/sale_purchase_requisition/readme/ROADMAP.rst
odoo/addons/sale_purchase_requisition/readme/USAGE.rst
odoo/addons/sale_purchase_requisition/security/ir.model.access.csv
odoo/addons/sale_purchase_requisition/security/sale_purchase_requisition_security.xml
odoo/addons/sale_purchase_requisition/static/description/icon.png
odoo/addons/sale_purchase_requisition/static/description/index.html
odoo/addons/sale_purchase_requisition/tests/__init__.py
odoo/addons/sale_purchase_requisition/tests/test_sale_purchase_requisition.py
odoo/addons/sale_purchase_requisition/views/purchase_requisition.xml
odoo/addons/sale_purchase_requisition/views/sale_order.xml
odoo14_addon_sale_purchase_requisition-14.0.1.0.1.dist-info/METADATA
odoo14_addon_sale_purchase_requisition-14.0.1.0.1.dist-info/WHEEL
odoo14_addon_sale_purchase_requisition-14.0.1.0.1.dist-info/top_level.txt
odoo14_addon_sale_purchase_requisition-14.0.1.0.1.dist-info/RECORD
